sqooler/__init__.py
sqooler/cli.py
sqooler/schemes.py
sqooler/security.py
sqooler/spoolers.py
sqooler/storage_providers/__init__.py
sqooler/storage_providers/base.py
sqooler/storage_providers/dropbox.py
sqooler/storage_providers/local.py
sqooler/storage_providers/mongodb.py
sqooler/utils.py
sqooler-0.9.0.dist-info/LICENSE
sqooler-0.9.0.dist-info/METADATA
sqooler-0.9.0.dist-info/WHEEL
sqooler-0.9.0.dist-info/entry_points.txt
sqooler-0.9.0.dist-info/RECORD
