Metadata-Version: 2.1
Name: sqooler
Version: 0.9.0
Summary: Code that enables validated cloud access to quantum hardware (simulators)
Home-page: https://github.com/Alqor-UG/sqooler
License: Unlicense
Keywords: pydantic,quantum-hardware,sdk-python
Author: fretchen
Author-email: fred.jendrzejewski@gmail.com
Requires-Python: >=3.10,<4.0
Classifier: License :: OSI Approved
Classifier: Programming Language :: Python :: 3
Classifier: Programming Language :: Python :: 3.10
Classifier: Programming Language :: Python :: 3.11
Classifier: Programming Language :: Python :: 3.12
Requires-Dist: click (>=8.1.7,<9.0.0)
Requires-Dist: cryptography (>=42.0.5,<43.0.0)
Requires-Dist: dropbox (>=11.36.2,<12.0.0)
Requires-Dist: pydantic (>=2.3.0,<3.0.0)
Requires-Dist: pymongo (>=4.3.3,<5.0.0)
Requires-Dist: regex (>=2024.5.15,<2025.0.0)
Requires-Dist: setuptools (>=70.0.0,<71.0.0)
Project-URL: Documentation, https://alqor-ug.github.io/sqooler
Project-URL: Repository, https://github.com/Alqor-UG/sqooler
